ruulang_runtime/__init__.py
ruulang_runtime/registry.py
ruulang_runtime-0.1.2.dist-info/WHEEL
ruulang_runtime-0.1.2.dist-info/METADATA
ruulang_runtime-0.1.2.dist-info/RECORD
